rboot
