Metadata-Version: 1.1
Name: rboot
Version: 0.1.1
Summary: Replacment Bootstrap
Home-page: http://www.amirsani.com
Author: Amir Sani
Author-email: reachme@amirsani.com
License: UNKNOWN
Download-URL: https://github.com/amirsani/rboot_python
Platform: UNKNOWN
